auth_jwt_validator/__init__.py
auth_jwt_validator/config.py
auth_jwt_validator/exceptions.py
auth_jwt_validator/settings.py
auth_jwt_validator/decorators/__init__.py
auth_jwt_validator/decorators/drf.py
auth_jwt_validator/decorators/graphql.py
auth_jwt_validator/drf/__init__.py
auth_jwt_validator/drf/permissions.py
auth_jwt_validator/utils/__init__.py
auth_jwt_validator/utils/cache.py
auth_jwt_validator/validators/__init__.py
auth_jwt_validator/validators/jwks_fetcher.py
auth_jwt_validator/validators/jwt_validator.py
auth_jwt_validator-0.1.9.dist-info/licenses/LICENSE
auth_jwt_validator-0.1.9.dist-info/METADATA
auth_jwt_validator-0.1.9.dist-info/WHEEL
auth_jwt_validator-0.1.9.dist-info/top_level.txt
auth_jwt_validator-0.1.9.dist-info/RECORD
